{"cameraMode":{"drawMode":0,"name":"Shaded","section":"Shading Mode"},"sceneLighting":true,"audioPlay":false,"sceneViewState":{"showFog":true,"showMaterialUpdate":false,"showSkybox":true,"showFlares":true,"showImageEffects":true,"showParticleSystems":true},"in2DMode":false,"pivot":{"x":11.688583374023438,"y":86.45450592041016,"z":-1.0977058410644532},"rotation":{"x":-0.21609018743038178,"y":0.0023554719518870117,"z":-0.0005213532713241875,"w":-0.9763704538345337},"size":3.356921911239624,"orthographic":false}